setup.py
dispersers/__init__.py
dispersers/analyses.py
dispersers/database_utils.py
dispersers/disperser_agents.py
dispersers/topology.py
dispersers/tree_agent.py
dispersers/world.py
dispersers.egg-info/PKG-INFO
dispersers.egg-info/SOURCES.txt
dispersers.egg-info/dependency_links.txt
dispersers.egg-info/not-zip-safe
dispersers.egg-info/requires.txt
dispersers.egg-info/top_level.txt