Metadata-Version: 1.0
Name: dispersers
Version: 0.1.1
Summary: Agent-based models for mechanistic simulations of seed dispersers
Home-page: http://github.com/fsfrazao/Dispersers
Author: Fabio Frazao
Author-email: fsfrazao@gmail.com
License: GNU General Public License v3.0
Platform: UNKNOWN
